image_processing_DIO/__init__.py
image_processing_DIO/processing/__init__.py
image_processing_DIO/processing/combination.py
image_processing_DIO/processing/transformation.py
image_processing_DIO/utils/__init__.py
image_processing_DIO/utils/io.py
image_processing_DIO/utils/plot.py
image_processing_DIO-0.0.2.dist-info/METADATA
image_processing_DIO-0.0.2.dist-info/WHEEL
image_processing_DIO-0.0.2.dist-info/top_level.txt
image_processing_DIO-0.0.2.dist-info/RECORD
