Metadata-Version: 2.1
Name: image-processing-DIO
Version: 0.0.2
Summary: Package basic of processing image
Home-page: https://github.com/ernestojr-7/image-processing-DIO
Author: my_name
Author-email: santosunior@gmail.com
License: UNKNOWN
Platform: UNKNOWN
Requires-Python: >=3.8
